[{"firstname":"Léonie","lastname":"Matyugin","email":"smatyugin0@tumblr.com","phonenumber":"986-982-1323","company":"Teklist","streetnumber":"832","street":"Larry","zipcode":"62-610-3663","city":"Kwolla","country":"Nigeria","task_associated":"Propithecus verreauxi","task_deadline":"12/9/2020","priority":1,"comments":"Hatity"},
    {"firstname":"Dà","lastname":"Rushbrooke","email":"hrushbrooke1@newsvine.com","phonenumber":"895-696-7340","company":"Gevee","streetnumber":"0","street":"Norway Maple","zipcode":"08-120-4095","city":"Zwedru","country":"Liberia","task_associated":"Falco peregrinus","task_deadline":"7/4/2020","priority":3,"comments":"Wrapsafe"},
    {"firstname":"Lyséa","lastname":"Prahl","email":"mprahl2@amazonaws.com","phonenumber":"835-968-7219","company":"Quimba","streetnumber":"697","street":"La Follette","zipcode":"72-571-3414","city":"Seremban","country":"Malaysia","task_associated":"Myrmecobius fasciatus","task_deadline":"11/22/2020","priority":2,"comments":"Andalax"},
    {"firstname":"Dorothée","lastname":"Swalteridge","email":"fswalteridge3@php.net","phonenumber":"410-676-2725","company":"Thoughtstorm","streetnumber":"32","street":"Londonderry","zipcode":"91-126-2067","city":"Sourotí","country":"Greece","task_associated":"Lama glama","task_deadline":"5/2/2020","priority":3,"comments":"Overhold"},
    {"firstname":"Marie-thérèse","lastname":"Pacher","email":"epacher4@skype.com","phonenumber":"480-467-4885","company":"Fatz","streetnumber":"63","street":"Hooker","zipcode":"33-247-9875","city":"Fanzhuang","country":"China","task_associated":"Centrocercus urophasianus","task_deadline":"7/19/2020","priority":1,"comments":"Flexidy"},
    {"firstname":"Sòng","lastname":"Twiname","email":"rtwiname5@dion.ne.jp","phonenumber":"422-932-9913","company":"Aimbu","streetnumber":"92712","street":"Warner","zipcode":"49-738-1771","city":"Sigeng","country":"China","task_associated":"Columba livia","task_deadline":"11/10/2020","priority":2,"comments":"Subin"},
    {"firstname":"Maéna","lastname":"Yushkov","email":"eyushkov6@discovery.com","phonenumber":"320-964-8144","company":"Youopia","streetnumber":"9","street":"Union","zipcode":"39-177-1249","city":"Corral","country":"Chile","task_associated":"Canis aureus","task_deadline":"12/12/2020","priority":2,"comments":"Fix San"},
    {"firstname":"Maïlys","lastname":"Skyrme","email":"sskyrme7@pagesperso-orange.fr","phonenumber":"680-629-2706","company":"Babblestorm","streetnumber":"4","street":"Nobel","zipcode":"49-267-1342","city":"Jasienica Rosielna","country":"Poland","task_associated":"Lepus arcticus","task_deadline":"10/16/2020","priority":1,"comments":"Lotstring"},
    {"firstname":"Loïc","lastname":"Krochmann","email":"ckrochmann8@cam.ac.uk","phonenumber":"553-266-6169","company":"Zoombeat","streetnumber":"77818","street":"Bunker Hill","zipcode":"46-401-7666","city":"Nabire","country":"Indonesia","task_associated":"Catharacta skua","task_deadline":"2/15/2020","priority":1,"comments":"Andalax"},
    {"firstname":"Lorène","lastname":"Tremblett","email":"etremblett9@google.co.uk","phonenumber":"987-190-0981","company":"Zoonoodle","streetnumber":"2","street":"Harper","zipcode":"05-428-5304","city":"Cervantes","country":"Philippines","task_associated":"Felis concolor","task_deadline":"10/12/2020","priority":3,"comments":"Zathin"}]
